{
  "team": "Rising Pune Supergiants",
  "slug": "rps",
  "season": "2017",
  "season_year": 2017,
  "label": "Rising Pune Supergiants",
  "header": {
    "matches": 16,
    "wins": 10,
    "losses": 6,
    "win_pct": 0.625,
    "team_total_tilt": 2.59887,
    "team_tilt_per_match": 0.16243,
    "position_est": 2
  },
  "batting_stats": {
    "runs": 2370,
    "balls": 1844,
    "sr": 128.52,
    "fours": 197,
    "sixes": 89,
    "dots": 701
  },
  "bowling_stats": {
    "wickets": 113,
    "balls": 1865,
    "runs_conceded": 2436,
    "economy": 7.84
  },
  "roster": [
    {
      "player": "Lockie Ferguson",
      "slug": "lh-ferguson-2f9d0389",
      "matches": 4,
      "batting_stats": {
        "runs": 1,
        "innings": 1,
        "balls": 1,
        "avg": 1.0,
        "sr": 100.0,
        "hs": 1,
        "not_outs": 1,
        "fifties": 0,
        "hundreds": 0
      },
      "bowling_stats": {
        "wickets": 5,
        "innings": 4,
        "balls": 78,
        "runs_conceded": 96,
        "avg": 19.2,
        "economy": 7.38,
        "best_figures": "3/8"
      },
      "batting_tilt_per_match": null,
      "bowling_tilt_per_match": 0.13242,
      "shrunk_total_tilt_per_match": 0.06194,
      "total_tilt": 0.52968
    },
    {
      "player": "Imran Tahir",
      "slug": "imran-tahir-acee4cc4",
      "matches": 12,
      "batting_stats": {
        "runs": 0,
        "innings": 1,
        "balls": 2,
        "avg": 0.0,
        "sr": 0.0,
        "hs": 0,
        "not_outs": 1,
        "fifties": 0,
        "hundreds": 0
      },
      "bowling_stats": {
        "wickets": 19,
        "innings": 12,
        "balls": 282,
        "runs_conceded": 370,
        "avg": 19.47,
        "economy": 7.87,
        "best_figures": "4/27"
      },
      "batting_tilt_per_match": null,
      "bowling_tilt_per_match": 0.08504,
      "shrunk_total_tilt_per_match": 0.06164,
      "total_tilt": 1.02046
    },
    {
      "player": "Jaydev Unadkat",
      "slug": "jd-unadkat-1e66c162",
      "matches": 12,
      "batting_stats": {
        "runs": 2,
        "innings": 1,
        "balls": 5,
        "avg": 2.0,
        "sr": 40.0,
        "hs": 2,
        "not_outs": 1,
        "fifties": 0,
        "hundreds": 0
      },
      "bowling_stats": {
        "wickets": 27,
        "innings": 12,
        "balls": 275,
        "runs_conceded": 330,
        "avg": 12.22,
        "economy": 7.2,
        "best_figures": "5/30"
      },
      "batting_tilt_per_match": null,
      "bowling_tilt_per_match": 0.08038,
      "shrunk_total_tilt_per_match": 0.05773,
      "total_tilt": 0.95948
    },
    {
      "player": "Washington Sundar",
      "slug": "washington-sundar-f19ccfad",
      "matches": 10,
      "batting_stats": {
        "runs": 9,
        "innings": 5,
        "balls": 12,
        "avg": 9.0,
        "sr": 75.0,
        "hs": 5,
        "not_outs": 5,
        "fifties": 0,
        "hundreds": 0
      },
      "bowling_stats": {
        "wickets": 9,
        "innings": 10,
        "balls": 180,
        "runs_conceded": 189,
        "avg": 21.0,
        "economy": 6.3,
        "best_figures": "3/16"
      },
      "batting_tilt_per_match": null,
      "bowling_tilt_per_match": 0.08218,
      "shrunk_total_tilt_per_match": 0.05031,
      "total_tilt": 0.74282
    },
    {
      "player": "Ben Stokes",
      "slug": "ba-stokes-e087956b",
      "matches": 12,
      "batting_stats": {
        "runs": 316,
        "innings": 11,
        "balls": 221,
        "avg": 31.6,
        "sr": 142.99,
        "hs": 103,
        "not_outs": 1,
        "fifties": 2,
        "hundreds": 1
      },
      "bowling_stats": {
        "wickets": 14,
        "innings": 12,
        "balls": 264,
        "runs_conceded": 327,
        "avg": 23.36,
        "economy": 7.43,
        "best_figures": "3/20"
      },
      "batting_tilt_per_match": 0.01738,
      "bowling_tilt_per_match": 0.03202,
      "shrunk_total_tilt_per_match": 0.03315,
      "total_tilt": 0.57542
    },
    {
      "player": "Daniel Christian",
      "slug": "dt-christian-2a2e6343",
      "matches": 13,
      "batting_stats": {
        "runs": 79,
        "innings": 9,
        "balls": 49,
        "avg": 15.8,
        "sr": 161.22,
        "hs": 17,
        "not_outs": 4,
        "fifties": 0,
        "hundreds": 0
      },
      "bowling_stats": {
        "wickets": 12,
        "innings": 13,
        "balls": 240,
        "runs_conceded": 303,
        "avg": 25.25,
        "economy": 7.57,
        "best_figures": "2/23"
      },
      "batting_tilt_per_match": null,
      "bowling_tilt_per_match": 0.02771,
      "shrunk_total_tilt_per_match": 0.03107,
      "total_tilt": 0.57394
    },
    {
      "player": "Rahul Tripathi",
      "slug": "ra-tripathi-77255a9e",
      "matches": 14,
      "batting_stats": {
        "runs": 391,
        "innings": 14,
        "balls": 267,
        "avg": 32.58,
        "sr": 146.44,
        "hs": 93,
        "not_outs": 2,
        "fifties": 2,
        "hundreds": 0
      },
      "bowling_stats": {
        "wickets": 0,
        "innings": 1,
        "balls": 6,
        "runs_conceded": 12,
        "avg": 12.0,
        "economy": 12.0,
        "best_figures": "0/12"
      },
      "batting_tilt_per_match": 0.02516,
      "bowling_tilt_per_match": null,
      "shrunk_total_tilt_per_match": 0.01352,
      "total_tilt": 0.29576
    },
    {
      "player": "Shardul Thakur",
      "slug": "sn-thakur-1abb78f8",
      "matches": 12,
      "batting_stats": {
        "runs": 0,
        "innings": 3,
        "balls": 3,
        "avg": 0.0,
        "sr": 0.0,
        "hs": 0,
        "not_outs": 0,
        "fifties": 0,
        "hundreds": 0
      },
      "bowling_stats": {
        "wickets": 13,
        "innings": 12,
        "balls": 229,
        "runs_conceded": 319,
        "avg": 24.54,
        "economy": 8.36,
        "best_figures": "4/37"
      },
      "batting_tilt_per_match": null,
      "bowling_tilt_per_match": 0.03594,
      "shrunk_total_tilt_per_match": 0.01157,
      "total_tilt": 0.23826
    },
    {
      "player": "Manoj Tiwary",
      "slug": "mk-tiwary-26e5cabf",
      "matches": 13,
      "batting_stats": {
        "runs": 324,
        "innings": 13,
        "balls": 236,
        "avg": 36.0,
        "sr": 137.29,
        "hs": 60,
        "not_outs": 4,
        "fifties": 2,
        "hundreds": 0
      },
      "bowling_stats": null,
      "batting_tilt_per_match": 0.00483,
      "bowling_tilt_per_match": null,
      "shrunk_total_tilt_per_match": 0.00031,
      "total_tilt": 0.06279
    },
    {
      "player": "Steve Smith",
      "slug": "spd-smith-30a45b23",
      "matches": 15,
      "batting_stats": {
        "runs": 472,
        "innings": 15,
        "balls": 387,
        "avg": 39.33,
        "sr": 121.96,
        "hs": 84,
        "not_outs": 3,
        "fifties": 3,
        "hundreds": 0
      },
      "bowling_stats": null,
      "batting_tilt_per_match": -0.00248,
      "bowling_tilt_per_match": null,
      "shrunk_total_tilt_per_match": -0.00509,
      "total_tilt": -0.0372
    },
    {
      "player": "Adam Zampa",
      "slug": "a-zampa-14f96089",
      "matches": 6,
      "batting_stats": {
        "runs": 5,
        "innings": 1,
        "balls": 7,
        "avg": 5.0,
        "sr": 71.43,
        "hs": 5,
        "not_outs": 0,
        "fifties": 0,
        "hundreds": 0
      },
      "bowling_stats": {
        "wickets": 7,
        "innings": 6,
        "balls": 119,
        "runs_conceded": 164,
        "avg": 23.43,
        "economy": 8.27,
        "best_figures": "2/22"
      },
      "batting_tilt_per_match": null,
      "bowling_tilt_per_match": -0.00998,
      "shrunk_total_tilt_per_match": -0.01303,
      "total_tilt": -0.0678
    },
    {
      "player": "Ajinkya Rahane",
      "slug": "am-rahane-29e95537",
      "matches": 16,
      "batting_stats": {
        "runs": 382,
        "innings": 16,
        "balls": 323,
        "avg": 25.47,
        "sr": 118.27,
        "hs": 60,
        "not_outs": 1,
        "fifties": 2,
        "hundreds": 0
      },
      "bowling_stats": null,
      "batting_tilt_per_match": -0.0368,
      "bowling_tilt_per_match": null,
      "shrunk_total_tilt_per_match": -0.03294,
      "total_tilt": -0.58874
    },
    {
      "player": "Faf du Plessis",
      "slug": "f-du-plessis-3355b542",
      "matches": 1,
      "batting_stats": {
        "runs": 8,
        "innings": 1,
        "balls": 7,
        "avg": 8.0,
        "sr": 114.29,
        "hs": 8,
        "not_outs": 0,
        "fifties": 0,
        "hundreds": 0
      },
      "bowling_stats": null,
      "batting_tilt_per_match": null,
      "bowling_tilt_per_match": null,
      "shrunk_total_tilt_per_match": -0.02102,
      "total_tilt": -0.03959
    },
    {
      "player": "Rajat Bhatia",
      "slug": "r-bhatia-33a364a6",
      "matches": 3,
      "batting_stats": {
        "runs": 16,
        "innings": 1,
        "balls": 17,
        "avg": 16.0,
        "sr": 94.12,
        "hs": 16,
        "not_outs": 0,
        "fifties": 0,
        "hundreds": 0
      },
      "bowling_stats": {
        "wickets": 2,
        "innings": 3,
        "balls": 42,
        "runs_conceded": 55,
        "avg": 27.5,
        "economy": 7.86,
        "best_figures": "2/14"
      },
      "batting_tilt_per_match": null,
      "bowling_tilt_per_match": null,
      "shrunk_total_tilt_per_match": -0.02704,
      "total_tilt": -0.12152
    },
    {
      "player": "Mahendra Singh Dhoni",
      "slug": "ms-dhoni-4a8a2e3b",
      "matches": 15,
      "batting_stats": {
        "runs": 290,
        "innings": 15,
        "balls": 250,
        "avg": 26.36,
        "sr": 116.0,
        "hs": 61,
        "not_outs": 4,
        "fifties": 1,
        "hundreds": 0
      },
      "bowling_stats": null,
      "batting_tilt_per_match": -0.04846,
      "bowling_tilt_per_match": null,
      "shrunk_total_tilt_per_match": -0.04213,
      "total_tilt": -0.72693
    },
    {
      "player": "Mayank Agarwal",
      "slug": "ma-agarwal-00ea847a",
      "matches": 3,
      "batting_stats": {
        "runs": 26,
        "innings": 3,
        "balls": 27,
        "avg": 8.67,
        "sr": 96.3,
        "hs": 20,
        "not_outs": 0,
        "fifties": 0,
        "hundreds": 0
      },
      "bowling_stats": null,
      "batting_tilt_per_match": null,
      "bowling_tilt_per_match": null,
      "shrunk_total_tilt_per_match": -0.03217,
      "total_tilt": -0.15548
    },
    {
      "player": "Rahul Chahar",
      "slug": "rd-chahar-2ed569a0",
      "matches": 2,
      "batting_stats": {
        "runs": 3,
        "innings": 1,
        "balls": 2,
        "avg": 3.0,
        "sr": 150.0,
        "hs": 3,
        "not_outs": 1,
        "fifties": 0,
        "hundreds": 0
      },
      "bowling_stats": {
        "wickets": 2,
        "innings": 2,
        "balls": 42,
        "runs_conceded": 59,
        "avg": 29.5,
        "economy": 8.43,
        "best_figures": "1/33"
      },
      "batting_tilt_per_match": null,
      "bowling_tilt_per_match": null,
      "shrunk_total_tilt_per_match": -0.03222,
      "total_tilt": -0.12358
    },
    {
      "player": "Ashok Dinda",
      "slug": "ab-dinda-66b30f71",
      "matches": 3,
      "batting_stats": {
        "runs": 7,
        "innings": 1,
        "balls": 7,
        "avg": 7.0,
        "sr": 100.0,
        "hs": 7,
        "not_outs": 0,
        "fifties": 0,
        "hundreds": 0
      },
      "bowling_stats": {
        "wickets": 2,
        "innings": 3,
        "balls": 60,
        "runs_conceded": 121,
        "avg": 60.5,
        "economy": 12.1,
        "best_figures": "1/58"
      },
      "batting_tilt_per_match": null,
      "bowling_tilt_per_match": -0.07342,
      "shrunk_total_tilt_per_match": -0.04157,
      "total_tilt": -0.21772
    },
    {
      "player": "Ankit Sharma",
      "slug": "ankit-sharma-24d94623",
      "matches": 1,
      "batting_stats": {
        "runs": 25,
        "innings": 1,
        "balls": 15,
        "avg": 25.0,
        "sr": 166.67,
        "hs": 25,
        "not_outs": 0,
        "fifties": 0,
        "hundreds": 0
      },
      "bowling_stats": {
        "wickets": 0,
        "innings": 1,
        "balls": 6,
        "runs_conceded": 16,
        "avg": 16.0,
        "economy": 16.0,
        "best_figures": "0/16"
      },
      "batting_tilt_per_match": null,
      "bowling_tilt_per_match": null,
      "shrunk_total_tilt_per_match": -0.02883,
      "total_tilt": -0.07571
    },
    {
      "player": "Deepak Chahar",
      "slug": "dl-chahar-23eeb873",
      "matches": 3,
      "batting_stats": {
        "runs": 14,
        "innings": 1,
        "balls": 6,
        "avg": 14.0,
        "sr": 233.33,
        "hs": 14,
        "not_outs": 0,
        "fifties": 0,
        "hundreds": 0
      },
      "bowling_stats": {
        "wickets": 1,
        "innings": 3,
        "balls": 42,
        "runs_conceded": 75,
        "avg": 75.0,
        "economy": 10.71,
        "best_figures": "1/36"
      },
      "batting_tilt_per_match": null,
      "bowling_tilt_per_match": null,
      "shrunk_total_tilt_per_match": -0.04576,
      "total_tilt": -0.24549
    }
  ],
  "matches": [
    {
      "match_id": "1082592",
      "date": "2017-04-06",
      "opponent": "Mumbai Indians",
      "team_score": "187/3",
      "opponent_score": "184/8",
      "winner": "Rising Pune Supergiants",
      "team_total_tilt": 0.39833
    },
    {
      "match_id": "1082594",
      "date": "2017-04-08",
      "opponent": "Punjab Kings",
      "team_score": "163/6",
      "opponent_score": "164/4",
      "winner": "Punjab Kings",
      "team_total_tilt": -0.08428
    },
    {
      "match_id": "1082599",
      "date": "2017-04-11",
      "opponent": "Delhi Capitals",
      "team_score": "108/10",
      "opponent_score": "205/4",
      "winner": "Delhi Capitals",
      "team_total_tilt": -0.73303
    },
    {
      "match_id": "1082603",
      "date": "2017-04-14",
      "opponent": "Gujarat Lions",
      "team_score": "171/8",
      "opponent_score": "172/3",
      "winner": "Gujarat Lions",
      "team_total_tilt": -0.30469
    },
    {
      "match_id": "1082607",
      "date": "2017-04-16",
      "opponent": "Royal Challengers Bangalore",
      "team_score": "161/8",
      "opponent_score": "134/9",
      "winner": "Rising Pune Supergiants",
      "team_total_tilt": 0.48408
    },
    {
      "match_id": "1082615",
      "date": "2017-04-22",
      "opponent": "Sunrisers Hyderabad",
      "team_score": "179/4",
      "opponent_score": "176/3",
      "winner": "Rising Pune Supergiants",
      "team_total_tilt": 0.24013
    },
    {
      "match_id": "1082618",
      "date": "2017-04-24",
      "opponent": "Mumbai Indians",
      "team_score": "160/6",
      "opponent_score": "157/8",
      "winner": "Rising Pune Supergiants",
      "team_total_tilt": 0.32563
    },
    {
      "match_id": "1082620",
      "date": "2017-04-26",
      "opponent": "Kolkata Knight Riders",
      "team_score": "182/5",
      "opponent_score": "184/3",
      "winner": "Kolkata Knight Riders",
      "team_total_tilt": -0.29512
    },
    {
      "match_id": "1082624",
      "date": "2017-04-29",
      "opponent": "Royal Challengers Bangalore",
      "team_score": "157/3",
      "opponent_score": "96/9",
      "winner": "Rising Pune Supergiants",
      "team_total_tilt": 0.68467
    },
    {
      "match_id": "1082629",
      "date": "2017-05-01",
      "opponent": "Gujarat Lions",
      "team_score": "167/5",
      "opponent_score": "161/10",
      "winner": "Rising Pune Supergiants",
      "team_total_tilt": 0.24134
    },
    {
      "match_id": "1082631",
      "date": "2017-05-03",
      "opponent": "Kolkata Knight Riders",
      "team_score": "158/6",
      "opponent_score": "155/8",
      "winner": "Rising Pune Supergiants",
      "team_total_tilt": 0.4069
    },
    {
      "match_id": "1082634",
      "date": "2017-05-06",
      "opponent": "Sunrisers Hyderabad",
      "team_score": "148/8",
      "opponent_score": "136/9",
      "winner": "Rising Pune Supergiants",
      "team_total_tilt": 0.24646
    },
    {
      "match_id": "1082642",
      "date": "2017-05-12",
      "opponent": "Delhi Capitals",
      "team_score": "161/7",
      "opponent_score": "168/8",
      "winner": "Delhi Capitals",
      "team_total_tilt": -0.16176
    },
    {
      "match_id": "1082645",
      "date": "2017-05-14",
      "opponent": "Punjab Kings",
      "team_score": "78/1",
      "opponent_score": "73/10",
      "winner": "Rising Pune Supergiants",
      "team_total_tilt": 0.54144
    },
    {
      "match_id": "1082647",
      "date": "2017-05-16",
      "opponent": "Mumbai Indians",
      "team_score": "162/4",
      "opponent_score": "142/9",
      "winner": "Rising Pune Supergiants",
      "team_total_tilt": 0.55141
    },
    {
      "match_id": "1082650",
      "date": "2017-05-21",
      "opponent": "Mumbai Indians",
      "team_score": "128/6",
      "opponent_score": "129/8",
      "winner": "Mumbai Indians",
      "team_total_tilt": 0.05735
    }
  ]
}